{
    "id": "12551",
    "ident": "5NJ1",
    "type": "heliport",
    "name": "Oti Heliport",
    "latitude_deg": "40.80619812011719",
    "longitude_deg": "-74.9905014038086",
    "elevation_ft": "495",
    "continent": "NA",
    "iso_country": "US",
    "iso_region": "US-NJ",
    "municipality": "Oxford",
    "scheduled_service": "no",
    "gps_code": "5NJ1",
    "iata_code": "",
    "local_code": "5NJ1",
    "home_link": "",
    "wikipedia_link": "",
    "keywords": "",
    "country": {
        "id": "302755",
        "code": "US",
        "name": "United States",
        "continent": "NA",
        "wikipedia_link": "https://en.wikipedia.org/wiki/United_States",
        "keywords": "America"
    },
    "region": {
        "id": "306107",
        "code": "US-NJ",
        "local_code": "NJ",
        "name": "New Jersey",
        "continent": "NA",
        "iso_country": "US",
        "wikipedia_link": "https://en.wikipedia.org/wiki/New_Jersey",
        "keywords": ""
    }
}