{
    "id": "16397",
    "ident": "AZ09",
    "type": "closed",
    "name": "Sergio Private Airport",
    "latitude_deg": "34.799999",
    "longitude_deg": "-114.112999",
    "elevation_ft": "1900",
    "continent": "NA",
    "iso_country": "US",
    "iso_region": "US-AZ",
    "municipality": "Lake Havasu City",
    "scheduled_service": "no",
    "gps_code": "",
    "iata_code": "",
    "local_code": "",
    "home_link": "",
    "wikipedia_link": "",
    "keywords": "AZ09",
    "runways": [
        {
            "id": "247805",
            "airport_ref": "16397",
            "airport_ident": "AZ09",
            "length_ft": "1400",
            "width_ft": "50",
            "surface": "GVL",
            "lighted": "0",
            "closed": "0",
            "le_ident": "18",
            "le_latitude_deg": "",
            "le_longitude_deg": "",
            "le_elevation_ft": "",
            "le_heading_degT": "",
            "le_displaced_threshold_ft": "",
            "he_ident": "36",
            "he_latitude_deg": "",
            "he_longitude_deg": "",
            "he_elevation_ft": "",
            "he_heading_degT": "",
            "he_displaced_threshold_ft": ""
        }
    ],
    "country": {
        "id": "302755",
        "code": "US",
        "name": "United States",
        "continent": "NA",
        "wikipedia_link": "https://en.wikipedia.org/wiki/United_States",
        "keywords": "America"
    },
    "region": {
        "id": "306079",
        "code": "US-AZ",
        "local_code": "AZ",
        "name": "Arizona",
        "continent": "NA",
        "iso_country": "US",
        "wikipedia_link": "https://en.wikipedia.org/wiki/Arizona",
        "keywords": ""
    }
}