{
    "id": "337976",
    "ident": "BR-1290",
    "type": "heliport",
    "name": "Tênis Camp Heliport",
    "latitude_deg": "-22.565866",
    "longitude_deg": "-47.073833",
    "elevation_ft": "2024",
    "continent": "SA",
    "iso_country": "BR",
    "iso_region": "BR-SP",
    "municipality": "Artur Nogueira",
    "scheduled_service": "no",
    "gps_code": "SJTE",
    "iata_code": "",
    "local_code": "SP0662",
    "home_link": "",
    "wikipedia_link": "",
    "keywords": "",
    "country": {
        "id": "302791",
        "code": "BR",
        "name": "Brazil",
        "continent": "SA",
        "wikipedia_link": "https://en.wikipedia.org/wiki/Brazil",
        "keywords": "Brasil, Brasilian"
    },
    "region": {
        "id": "303224",
        "code": "BR-SP",
        "local_code": "SP",
        "name": "São Paulo",
        "continent": "SA",
        "iso_country": "BR",
        "wikipedia_link": "https://en.wikipedia.org/wiki/São_Paulo",
        "keywords": ""
    }
}