{
    "id": "16948",
    "ident": "CO95",
    "type": "small_airport",
    "name": "True Grit South Airport",
    "latitude_deg": "38.052799",
    "longitude_deg": "-107.980003",
    "elevation_ft": "9580",
    "continent": "NA",
    "iso_country": "US",
    "iso_region": "US-CO",
    "municipality": "Telluride",
    "scheduled_service": "no",
    "gps_code": "CO95",
    "iata_code": "",
    "local_code": "CO95",
    "home_link": "",
    "wikipedia_link": "",
    "keywords": "Wilson Ranch",
    "runways": [
        {
            "id": "255916",
            "airport_ref": "16948",
            "airport_ident": "CO95",
            "length_ft": "1500",
            "width_ft": "30",
            "surface": "TURF",
            "lighted": "0",
            "closed": "0",
            "le_ident": "10",
            "le_latitude_deg": "",
            "le_longitude_deg": "",
            "le_elevation_ft": "",
            "le_heading_degT": "",
            "le_displaced_threshold_ft": "",
            "he_ident": "28",
            "he_latitude_deg": "",
            "he_longitude_deg": "",
            "he_elevation_ft": "",
            "he_heading_degT": "",
            "he_displaced_threshold_ft": ""
        },
        {
            "id": "255917",
            "airport_ref": "16948",
            "airport_ident": "CO95",
            "length_ft": "4000",
            "width_ft": "60",
            "surface": "TURF",
            "lighted": "0",
            "closed": "0",
            "le_ident": "18",
            "le_latitude_deg": "",
            "le_longitude_deg": "",
            "le_elevation_ft": "",
            "le_heading_degT": "",
            "le_displaced_threshold_ft": "",
            "he_ident": "36",
            "he_latitude_deg": "",
            "he_longitude_deg": "",
            "he_elevation_ft": "",
            "he_heading_degT": "",
            "he_displaced_threshold_ft": ""
        }
    ],
    "country": {
        "id": "302755",
        "code": "US",
        "name": "United States",
        "continent": "NA",
        "wikipedia_link": "https://en.wikipedia.org/wiki/United_States",
        "keywords": "America"
    },
    "region": {
        "id": "306081",
        "code": "US-CO",
        "local_code": "CO",
        "name": "Colorado",
        "continent": "NA",
        "iso_country": "US",
        "wikipedia_link": "https://en.wikipedia.org/wiki/Colorado",
        "keywords": ""
    },
    "navaids": [
        {
            "id": "87855",
            "filename": "Cones_VOR-DME_US",
            "ident": "ETL",
            "name": "Cones",
            "type": "VOR-DME",
            "frequency_khz": "110200",
            "latitude_deg": "38.04029846191406",
            "longitude_deg": "-108.25900268554688",
            "elevation_ft": "8460",
            "iso_country": "US",
            "dme_frequency_khz": "110200",
            "dme_channel": "039X",
            "dme_latitude_deg": "",
            "dme_longitude_deg": "",
            "dme_elevation_ft": "",
            "slaved_variation_deg": "12.001",
            "magnetic_variation_deg": "10.554",
            "usageType": "LO",
            "power": "MEDIUM",
            "associated_airport": "CO95"
        }
    ]
}