{
    "id": "28753",
    "ident": "EDQW",
    "type": "small_airport",
    "name": "Weiden in der Oberpfalz Airport",
    "latitude_deg": "49.67890167236328",
    "longitude_deg": "12.116399765014648",
    "elevation_ft": "1329",
    "continent": "EU",
    "iso_country": "DE",
    "iso_region": "DE-BY",
    "municipality": "Weiden in der Oberpfalz",
    "scheduled_service": "no",
    "gps_code": "EDQW",
    "iata_code": "",
    "local_code": "",
    "home_link": "",
    "wikipedia_link": "",
    "keywords": "Weiden/Opf. Airport",
    "runways": [
        {
            "id": "269336",
            "airport_ref": "28753",
            "airport_ident": "EDQW",
            "length_ft": "1700",
            "width_ft": "35",
            "surface": "Concrete",
            "lighted": "0",
            "closed": "0",
            "le_ident": "14",
            "le_latitude_deg": "",
            "le_longitude_deg": "",
            "le_elevation_ft": "",
            "le_heading_degT": "",
            "le_displaced_threshold_ft": "",
            "he_ident": "32",
            "he_latitude_deg": "",
            "he_longitude_deg": "",
            "he_elevation_ft": "",
            "he_heading_degT": "",
            "he_displaced_threshold_ft": ""
        }
    ],
    "freqs": [
        {
            "id": "75293",
            "airport_ref": "28753",
            "airport_ident": "EDQW",
            "type": "AFIS",
            "description": "",
            "frequency_mhz": "120.25"
        }
    ],
    "country": {
        "id": "302681",
        "code": "DE",
        "name": "Germany",
        "continent": "EU",
        "wikipedia_link": "https://en.wikipedia.org/wiki/Germany",
        "keywords": "Flughäfen in Deutschland"
    },
    "region": {
        "id": "303550",
        "code": "DE-BY",
        "local_code": "BY",
        "name": "Bavaria",
        "continent": "EU",
        "iso_country": "DE",
        "wikipedia_link": "https://en.wikipedia.org/wiki/Bavaria",
        "keywords": "Bayern"
    }
}