{
    "id": "30336",
    "ident": "EERI",
    "type": "small_airport",
    "name": "Ridali Airfield",
    "latitude_deg": "57.9399986267",
    "longitude_deg": "26.9790000916",
    "elevation_ft": "302",
    "continent": "EU",
    "iso_country": "EE",
    "iso_region": "EE-65",
    "municipality": "Suurküla",
    "scheduled_service": "no",
    "gps_code": "EERI",
    "iata_code": "",
    "local_code": "",
    "home_link": "",
    "wikipedia_link": "https://en.wikipedia.org/wiki/Ridali_Airfield",
    "keywords": "",
    "runways": [
        {
            "id": "263450",
            "airport_ref": "30336",
            "airport_ident": "EERI",
            "length_ft": "3937",
            "width_ft": "",
            "surface": "GRS",
            "lighted": "0",
            "closed": "0",
            "le_ident": "18",
            "le_latitude_deg": "",
            "le_longitude_deg": "",
            "le_elevation_ft": "",
            "le_heading_degT": "",
            "le_displaced_threshold_ft": "",
            "he_ident": "36",
            "he_latitude_deg": "",
            "he_longitude_deg": "",
            "he_elevation_ft": "",
            "he_heading_degT": "",
            "he_displaced_threshold_ft": ""
        }
    ],
    "country": {
        "id": "302683",
        "code": "EE",
        "name": "Estonia",
        "continent": "EU",
        "wikipedia_link": "https://en.wikipedia.org/wiki/Estonia",
        "keywords": ""
    },
    "region": {
        "id": "303682",
        "code": "EE-65",
        "local_code": "65",
        "name": "Põlva County",
        "continent": "EU",
        "iso_country": "EE",
        "wikipedia_link": "https://en.wikipedia.org/wiki/P%C3%B5lva_County",
        "keywords": ""
    }
}