{
    "id": "2315",
    "ident": "EFJO",
    "type": "medium_airport",
    "name": "Joensuu Airport",
    "latitude_deg": "62.662899017334",
    "longitude_deg": "29.607500076294",
    "elevation_ft": "398",
    "continent": "EU",
    "iso_country": "FI",
    "iso_region": "FI-IS",
    "municipality": "Joensuu / Liperi",
    "scheduled_service": "yes",
    "gps_code": "EFJO",
    "iata_code": "JOE",
    "local_code": "",
    "home_link": "http://www.finavia.fi/en/joensuu/",
    "wikipedia_link": "https://en.wikipedia.org/wiki/Joensuu_Airport",
    "keywords": "",
    "runways": [
        {
            "id": "235734",
            "airport_ref": "2315",
            "airport_ident": "EFJO",
            "length_ft": "8202",
            "width_ft": "171",
            "surface": "ASP",
            "lighted": "1",
            "closed": "0",
            "le_ident": "10",
            "le_latitude_deg": "62.6646",
            "le_longitude_deg": "29.5977",
            "le_elevation_ft": "398",
            "le_heading_degT": "110",
            "le_displaced_threshold_ft": "",
            "he_ident": "28",
            "he_latitude_deg": "62.6568",
            "he_longitude_deg": "29.6434",
            "he_elevation_ft": "364",
            "he_heading_degT": "290",
            "he_displaced_threshold_ft": ""
        },
        {
            "id": "235735",
            "airport_ref": "2315",
            "airport_ident": "EFJO",
            "length_ft": "3937",
            "width_ft": "98",
            "surface": "COM",
            "lighted": "0",
            "closed": "0",
            "le_ident": "17",
            "le_latitude_deg": "62.6622",
            "le_longitude_deg": "29.6076",
            "le_elevation_ft": "391",
            "le_heading_degT": "181",
            "le_displaced_threshold_ft": "",
            "he_ident": "35",
            "he_latitude_deg": "62.6514",
            "he_longitude_deg": "29.6073",
            "he_elevation_ft": "371",
            "he_heading_degT": "1",
            "he_displaced_threshold_ft": ""
        }
    ],
    "freqs": [
        {
            "id": "52089",
            "airport_ref": "2315",
            "airport_ident": "EFJO",
            "type": "ATIS",
            "description": "ATIS",
            "frequency_mhz": "115.7"
        },
        {
            "id": "52090",
            "airport_ref": "2315",
            "airport_ident": "EFJO",
            "type": "TWR",
            "description": "TWR",
            "frequency_mhz": "120.9"
        }
    ],
    "country": {
        "id": "302685",
        "code": "FI",
        "name": "Finland",
        "continent": "EU",
        "wikipedia_link": "https://en.wikipedia.org/wiki/Finland",
        "keywords": "Lentokentät, Suomen"
    },
    "region": {
        "id": "303801",
        "code": "FI-IS",
        "local_code": "IS",
        "name": "Eastern Finland",
        "continent": "EU",
        "iso_country": "FI",
        "wikipedia_link": "https://en.wikipedia.org/wiki/Eastern_Finland",
        "keywords": "Itä-Suomen lääni, Östra Finlands län"
    },
    "navaids": [
        {
            "id": "89523",
            "filename": "Josie_VOR-DME_FI",
            "ident": "JNS",
            "name": "Josie",
            "type": "VOR-DME",
            "frequency_khz": "115700",
            "latitude_deg": "62.660499572753906",
            "longitude_deg": "29.61050033569336",
            "elevation_ft": "413",
            "iso_country": "FI",
            "dme_frequency_khz": "115700",
            "dme_channel": "104X",
            "dme_latitude_deg": "",
            "dme_longitude_deg": "",
            "dme_elevation_ft": "",
            "slaved_variation_deg": "7.007",
            "magnetic_variation_deg": "9.455",
            "usageType": "RNAV",
            "power": "HIGH",
            "associated_airport": "EFJO"
        },
        {
            "id": "89528",
            "filename": "Joensuu_NDB_FI",
            "ident": "JOE",
            "name": "Joensuu",
            "type": "NDB",
            "frequency_khz": "325",
            "latitude_deg": "62.686100006103516",
            "longitude_deg": "29.47209930419922",
            "elevation_ft": "",
            "iso_country": "FI",
            "dme_frequency_khz": "",
            "dme_channel": "",
            "dme_latitude_deg": "",
            "dme_longitude_deg": "",
            "dme_elevation_ft": "",
            "slaved_variation_deg": "",
            "magnetic_variation_deg": "9.427",
            "usageType": "LO",
            "power": "LOW",
            "associated_airport": "EFJO"
        }
    ]
}