{
    "id": "17515",
    "ident": "GA41",
    "type": "small_airport",
    "name": "Daniels Airport",
    "latitude_deg": "32.61410140991211",
    "longitude_deg": "-82.2970962524414",
    "elevation_ft": "288",
    "continent": "NA",
    "iso_country": "US",
    "iso_region": "US-GA",
    "municipality": "Swainsboro",
    "scheduled_service": "no",
    "gps_code": "GA41",
    "iata_code": "",
    "local_code": "GA41",
    "home_link": "",
    "wikipedia_link": "",
    "keywords": "",
    "country": {
        "id": "302755",
        "code": "US",
        "name": "United States",
        "continent": "NA",
        "wikipedia_link": "https://en.wikipedia.org/wiki/United_States",
        "keywords": "America"
    },
    "region": {
        "id": "306086",
        "code": "US-GA",
        "local_code": "GA",
        "name": "Georgia",
        "continent": "NA",
        "iso_country": "US",
        "wikipedia_link": "https://en.wikipedia.org/wiki/Georgia",
        "keywords": ""
    }
}