{
    "id": "46562",
    "ident": "IN-0039",
    "type": "heliport",
    "name": "Lebong Helipad",
    "latitude_deg": "27.0590833333",
    "longitude_deg": "88.2777333333",
    "elevation_ft": "",
    "continent": "AS",
    "iso_country": "IN",
    "iso_region": "IN-WB",
    "municipality": "Lebong",
    "scheduled_service": "no",
    "gps_code": "",
    "iata_code": "",
    "local_code": "",
    "home_link": "",
    "wikipedia_link": "",
    "keywords": "",
    "country": {
        "id": "302634",
        "code": "IN",
        "name": "India",
        "continent": "AS",
        "wikipedia_link": "https://en.wikipedia.org/wiki/India",
        "keywords": ""
    },
    "region": {
        "id": "304198",
        "code": "IN-WB",
        "local_code": "WB",
        "name": "West Bengal",
        "continent": "AS",
        "iso_country": "IN",
        "wikipedia_link": "https://en.wikipedia.org/wiki/West_Bengal",
        "keywords": ""
    }
}