{
    "id": "19601",
    "ident": "KD50",
    "type": "small_airport",
    "name": "Crosby Municipal Airport",
    "latitude_deg": "48.92850112915039",
    "longitude_deg": "-103.2969970703125",
    "elevation_ft": "1950",
    "continent": "NA",
    "iso_country": "US",
    "iso_region": "US-ND",
    "municipality": "Crosby",
    "scheduled_service": "no",
    "gps_code": "KD50",
    "iata_code": "",
    "local_code": "D50",
    "home_link": "",
    "wikipedia_link": "",
    "keywords": "",
    "runways": [
        {
            "id": "243300",
            "airport_ref": "19601",
            "airport_ident": "KD50",
            "length_ft": "2700",
            "width_ft": "100",
            "surface": "GRS",
            "lighted": "0",
            "closed": "0",
            "le_ident": "03",
            "le_latitude_deg": "48.925",
            "le_longitude_deg": "-103.299",
            "le_elevation_ft": "1947",
            "le_heading_degT": "44.2",
            "le_displaced_threshold_ft": "",
            "he_ident": "21",
            "he_latitude_deg": "48.9303",
            "he_longitude_deg": "-103.291",
            "he_elevation_ft": "1939",
            "he_heading_degT": "224.2",
            "he_displaced_threshold_ft": ""
        },
        {
            "id": "243301",
            "airport_ref": "19601",
            "airport_ident": "KD50",
            "length_ft": "3800",
            "width_ft": "60",
            "surface": "ASP",
            "lighted": "1",
            "closed": "0",
            "le_ident": "12",
            "le_latitude_deg": "48.9322",
            "le_longitude_deg": "-103.303",
            "le_elevation_ft": "1950",
            "le_heading_degT": "135.1",
            "le_displaced_threshold_ft": "",
            "he_ident": "30",
            "he_latitude_deg": "48.9248",
            "he_longitude_deg": "-103.292",
            "he_elevation_ft": "1944",
            "he_heading_degT": "315.1",
            "he_displaced_threshold_ft": ""
        }
    ],
    "freqs": [
        {
            "id": "65671",
            "airport_ref": "19601",
            "airport_ident": "KD50",
            "type": "CNTR",
            "description": "SALT LAKE CITY CNTR",
            "frequency_mhz": "126.85"
        },
        {
            "id": "65672",
            "airport_ref": "19601",
            "airport_ident": "KD50",
            "type": "CTAF",
            "description": "CTAF",
            "frequency_mhz": "122.9"
        }
    ],
    "country": {
        "id": "302755",
        "code": "US",
        "name": "United States",
        "continent": "NA",
        "wikipedia_link": "https://en.wikipedia.org/wiki/United_States",
        "keywords": "America"
    },
    "region": {
        "id": "306104",
        "code": "US-ND",
        "local_code": "ND",
        "name": "North Dakota",
        "continent": "NA",
        "iso_country": "US",
        "wikipedia_link": "https://en.wikipedia.org/wiki/North_Dakota",
        "keywords": ""
    }
}