{
    "id": "3595",
    "ident": "KHTS",
    "type": "large_airport",
    "name": "Tri-State/Milton J. Ferguson Field",
    "latitude_deg": "38.36669922",
    "longitude_deg": "-82.55799866",
    "elevation_ft": "828",
    "continent": "NA",
    "iso_country": "US",
    "iso_region": "US-WV",
    "municipality": "Huntington",
    "scheduled_service": "yes",
    "gps_code": "KHTS",
    "iata_code": "HTS",
    "local_code": "HTS",
    "home_link": "",
    "wikipedia_link": "https://en.wikipedia.org/wiki/Tri-State_Airport",
    "keywords": "",
    "runways": [
        {
            "id": "241266",
            "airport_ref": "3595",
            "airport_ident": "KHTS",
            "length_ft": "3007",
            "width_ft": "60",
            "surface": "ASP",
            "lighted": "1",
            "closed": "1",
            "le_ident": "03",
            "le_latitude_deg": "38.3594",
            "le_longitude_deg": "-82.5567",
            "le_elevation_ft": "828",
            "le_heading_degT": "22.4",
            "le_displaced_threshold_ft": "",
            "he_ident": "21",
            "he_latitude_deg": "38.3671",
            "he_longitude_deg": "-82.5527",
            "he_elevation_ft": "827",
            "he_heading_degT": "202.4",
            "he_displaced_threshold_ft": ""
        },
        {
            "id": "241267",
            "airport_ref": "3595",
            "airport_ident": "KHTS",
            "length_ft": "6509",
            "width_ft": "150",
            "surface": "ASP",
            "lighted": "1",
            "closed": "0",
            "le_ident": "12",
            "le_latitude_deg": "38.3717",
            "le_longitude_deg": "-82.5701",
            "le_elevation_ft": "827",
            "le_heading_degT": "112.4",
            "le_displaced_threshold_ft": "",
            "he_ident": "30",
            "he_latitude_deg": "38.3648",
            "he_longitude_deg": "-82.549",
            "he_elevation_ft": "828",
            "he_heading_degT": "292.4",
            "he_displaced_threshold_ft": ""
        }
    ],
    "freqs": [
        {
            "id": "61507",
            "airport_ref": "3595",
            "airport_ident": "KHTS",
            "type": "A/D",
            "description": "HUNTINGTON APP/DEP",
            "frequency_mhz": "119.75"
        },
        {
            "id": "61508",
            "airport_ref": "3595",
            "airport_ident": "KHTS",
            "type": "ATIS",
            "description": "ATIS",
            "frequency_mhz": "125.2"
        },
        {
            "id": "61509",
            "airport_ref": "3595",
            "airport_ident": "KHTS",
            "type": "CLD",
            "description": "CLNC DEL",
            "frequency_mhz": "118.05"
        },
        {
            "id": "61510",
            "airport_ref": "3595",
            "airport_ident": "KHTS",
            "type": "GND",
            "description": "GND",
            "frequency_mhz": "121.9"
        },
        {
            "id": "61511",
            "airport_ref": "3595",
            "airport_ident": "KHTS",
            "type": "RDO",
            "description": "ELKINS RDO",
            "frequency_mhz": "122.2"
        },
        {
            "id": "61512",
            "airport_ref": "3595",
            "airport_ident": "KHTS",
            "type": "TWR",
            "description": "HUNTINGTON TWR",
            "frequency_mhz": "118.5"
        },
        {
            "id": "61513",
            "airport_ref": "3595",
            "airport_ident": "KHTS",
            "type": "UNIC",
            "description": "UNICOM",
            "frequency_mhz": "122.95"
        }
    ],
    "country": {
        "id": "302755",
        "code": "US",
        "name": "United States",
        "continent": "NA",
        "wikipedia_link": "https://en.wikipedia.org/wiki/United_States",
        "keywords": "America"
    },
    "region": {
        "id": "306126",
        "code": "US-WV",
        "local_code": "WV",
        "name": "West Virginia",
        "continent": "NA",
        "iso_country": "US",
        "wikipedia_link": "https://en.wikipedia.org/wiki/West_Virginia",
        "keywords": ""
    },
    "navaids": [
        {
            "id": "89020",
            "filename": "Huntt_NDB_US",
            "ident": "HT",
            "name": "Huntt",
            "type": "NDB",
            "frequency_khz": "226",
            "latitude_deg": "38.39889907836914",
            "longitude_deg": "-82.6552963256836",
            "elevation_ft": "758",
            "iso_country": "US",
            "dme_frequency_khz": "",
            "dme_channel": "",
            "dme_latitude_deg": "",
            "dme_longitude_deg": "",
            "dme_elevation_ft": "",
            "slaved_variation_deg": "",
            "magnetic_variation_deg": "-6.242",
            "usageType": "TERMINAL",
            "power": "LOW",
            "associated_airport": "KHTS"
        }
    ]
}