{
    "id": "322934",
    "ident": "KP-0069",
    "type": "heliport",
    "name": "Pukch’ang Airbase East Heliport",
    "latitude_deg": "39.49",
    "longitude_deg": "125.995417",
    "elevation_ft": "",
    "continent": "AS",
    "iso_country": "KP",
    "iso_region": "KP-03",
    "municipality": "Pukch’ang",
    "scheduled_service": "no",
    "gps_code": "",
    "iata_code": "",
    "local_code": "",
    "home_link": "",
    "wikipedia_link": "https://en.wikipedia.org/wiki/Pukchang_Airport",
    "keywords": "",
    "runways": [
        {
            "id": "323006",
            "airport_ref": "322934",
            "airport_ident": "KP-0069",
            "length_ft": "",
            "width_ft": "",
            "surface": "",
            "lighted": "0",
            "closed": "0",
            "le_ident": "10",
            "le_latitude_deg": "",
            "le_longitude_deg": "",
            "le_elevation_ft": "",
            "le_heading_degT": "",
            "le_displaced_threshold_ft": "",
            "he_ident": "28",
            "he_latitude_deg": "",
            "he_longitude_deg": "",
            "he_elevation_ft": "",
            "he_heading_degT": "",
            "he_displaced_threshold_ft": ""
        }
    ],
    "country": {
        "id": "302642",
        "code": "KP",
        "name": "North Korea",
        "continent": "AS",
        "wikipedia_link": "https://en.wikipedia.org/wiki/North_Korea",
        "keywords": ""
    },
    "region": {
        "id": "304395",
        "code": "KP-03",
        "local_code": "03",
        "name": "North Pyongan Province",
        "continent": "AS",
        "iso_country": "KP",
        "wikipedia_link": "https://en.wikipedia.org/wiki/North_Pyongan_Province",
        "keywords": "Pyonganbuk-do"
    }
}