{
    "id": "324225",
    "ident": "MX-0500",
    "type": "heliport",
    "name": "Vertientes Heliport",
    "latitude_deg": "19.408319",
    "longitude_deg": "-99.231275",
    "elevation_ft": "7579",
    "continent": "NA",
    "iso_country": "MX",
    "iso_region": "MX-DIF",
    "municipality": "Miguel Hidalgo",
    "scheduled_service": "no",
    "gps_code": "",
    "iata_code": "",
    "local_code": "HVS",
    "home_link": "",
    "wikipedia_link": "",
    "keywords": "",
    "country": {
        "id": "302747",
        "code": "MX",
        "name": "Mexico",
        "continent": "NA",
        "wikipedia_link": "https://en.wikipedia.org/wiki/Mexico",
        "keywords": "Aeropuertos de México"
    },
    "region": {
        "id": "304798",
        "code": "MX-DIF",
        "local_code": "DIF",
        "name": "Ciudad de México",
        "continent": "NA",
        "iso_country": "MX",
        "wikipedia_link": "https://en.wikipedia.org/wiki/Mexico_City",
        "keywords": ""
    }
}