{
    "id": "339957",
    "ident": "MX-1567",
    "type": "closed",
    "name": "Rancho Buenos Aires Airport",
    "latitude_deg": "24.639879",
    "longitude_deg": "-99.24993",
    "elevation_ft": "1083",
    "continent": "NA",
    "iso_country": "MX",
    "iso_region": "MX-TAM",
    "municipality": "Villagrán",
    "scheduled_service": "no",
    "gps_code": "",
    "iata_code": "",
    "local_code": "RBU",
    "home_link": "",
    "wikipedia_link": "",
    "keywords": "",
    "country": {
        "id": "302747",
        "code": "MX",
        "name": "Mexico",
        "continent": "NA",
        "wikipedia_link": "https://en.wikipedia.org/wiki/Mexico",
        "keywords": "Aeropuertos de México"
    },
    "region": {
        "id": "304817",
        "code": "MX-TAM",
        "local_code": "TAM",
        "name": "Tamaulipas",
        "continent": "NA",
        "iso_country": "MX",
        "wikipedia_link": "https://en.wikipedia.org/wiki/Tamaulipas",
        "keywords": ""
    }
}