{
    "id": "31900",
    "ident": "NCMG",
    "type": "small_airport",
    "name": "Mangaia Island Airport",
    "latitude_deg": "-21.895986557006836",
    "longitude_deg": "-157.9066619873047",
    "elevation_ft": "45",
    "continent": "OC",
    "iso_country": "CK",
    "iso_region": "CK-U-A",
    "municipality": "Mangaia Island",
    "scheduled_service": "yes",
    "gps_code": "NCMG",
    "iata_code": "MGS",
    "local_code": "",
    "home_link": "",
    "wikipedia_link": "https://en.wikipedia.org/wiki/Mangaia_Airport",
    "keywords": "",
    "runways": [
        {
            "id": "259677",
            "airport_ref": "31900",
            "airport_ident": "NCMG",
            "length_ft": "3274",
            "width_ft": "",
            "surface": "UNK",
            "lighted": "0",
            "closed": "0",
            "le_ident": "13",
            "le_latitude_deg": "",
            "le_longitude_deg": "",
            "le_elevation_ft": "45",
            "le_heading_degT": "",
            "le_displaced_threshold_ft": "",
            "he_ident": "31",
            "he_latitude_deg": "",
            "he_longitude_deg": "",
            "he_elevation_ft": "39",
            "he_heading_degT": "",
            "he_displaced_threshold_ft": ""
        }
    ],
    "country": {
        "id": "302765",
        "code": "CK",
        "name": "Cook Islands",
        "continent": "OC",
        "wikipedia_link": "https://en.wikipedia.org/wiki/Cook_Islands",
        "keywords": ""
    },
    "region": {
        "id": "303396",
        "code": "CK-U-A",
        "local_code": "U-A",
        "name": "(unassigned)",
        "continent": "OC",
        "iso_country": "CK",
        "wikipedia_link": "",
        "keywords": ""
    }
}