{
    "id": "325912",
    "ident": "PH-0064",
    "type": "heliport",
    "name": "General Gregorio Lim Marine Base Heliport",
    "latitude_deg": "14.267422",
    "longitude_deg": "120.626543",
    "elevation_ft": "",
    "continent": "AS",
    "iso_country": "PH",
    "iso_region": "PH-CAV",
    "municipality": "Bucana",
    "scheduled_service": "no",
    "gps_code": "",
    "iata_code": "",
    "local_code": "",
    "home_link": "",
    "wikipedia_link": "",
    "keywords": "General Gregorio Lim Marine Base, Bucana",
    "country": {
        "id": "302656",
        "code": "PH",
        "name": "Philippines",
        "continent": "AS",
        "wikipedia_link": "https://en.wikipedia.org/wiki/Philippines",
        "keywords": "Mga alternatibong byahe mula sa Pilipinas"
    },
    "region": {
        "id": "305078",
        "code": "PH-CAV",
        "local_code": "CAV",
        "name": "Cavite Province",
        "continent": "AS",
        "iso_country": "PH",
        "wikipedia_link": "https://en.wikipedia.org/wiki/Cavite_Province",
        "keywords": ""
    }
}