{
    "id": "41566",
    "ident": "PY-BFA",
    "type": "small_airport",
    "name": "Bahía Negra Airport",
    "latitude_deg": "-20.2245998383",
    "longitude_deg": "-58.1791992188",
    "elevation_ft": "277",
    "continent": "SA",
    "iso_country": "PY",
    "iso_region": "PY-16",
    "municipality": "Bahía Negra",
    "scheduled_service": "no",
    "gps_code": "SGBN",
    "iata_code": "BFA",
    "local_code": "",
    "home_link": "",
    "wikipedia_link": "",
    "keywords": "",
    "country": {
        "id": "302799",
        "code": "PY",
        "name": "Paraguay",
        "continent": "SA",
        "wikipedia_link": "https://en.wikipedia.org/wiki/Paraguay",
        "keywords": "Aeropuertos de Paraguay"
    },
    "region": {
        "id": "305196",
        "code": "PY-16",
        "local_code": "16",
        "name": "Alto Paraguay Department",
        "continent": "SA",
        "iso_country": "PY",
        "wikipedia_link": "https://en.wikipedia.org/wiki/Alto_Paraguay_Department",
        "keywords": ""
    }
}