{
    "id": "301542",
    "ident": "US-0195",
    "type": "heliport",
    "name": "South Jersey Healthcare Helipad",
    "latitude_deg": "39.444916666699996",
    "longitude_deg": "-75.06058333330002",
    "elevation_ft": "54",
    "continent": "NA",
    "iso_country": "US",
    "iso_region": "US-NJ",
    "municipality": "Vineland",
    "scheduled_service": "no",
    "gps_code": "",
    "iata_code": "",
    "local_code": "",
    "home_link": "",
    "wikipedia_link": "",
    "keywords": "H-497",
    "country": {
        "id": "302755",
        "code": "US",
        "name": "United States",
        "continent": "NA",
        "wikipedia_link": "https://en.wikipedia.org/wiki/United_States",
        "keywords": "America"
    },
    "region": {
        "id": "306107",
        "code": "US-NJ",
        "local_code": "NJ",
        "name": "New Jersey",
        "continent": "NA",
        "iso_country": "US",
        "wikipedia_link": "https://en.wikipedia.org/wiki/New_Jersey",
        "keywords": ""
    }
}