{
    "id": "27357",
    "ident": "YBBA",
    "type": "small_airport",
    "name": "Barraba Airport",
    "latitude_deg": "-30.38330078125",
    "longitude_deg": "150.60000610351562",
    "elevation_ft": "",
    "continent": "OC",
    "iso_country": "AU",
    "iso_region": "AU-NSW",
    "municipality": "",
    "scheduled_service": "no",
    "gps_code": "YBBA",
    "iata_code": "",
    "local_code": "",
    "home_link": "",
    "wikipedia_link": "",
    "keywords": "",
    "runways": [
        {
            "id": "258254",
            "airport_ref": "27357",
            "airport_ident": "YBBA",
            "length_ft": "3937",
            "width_ft": "",
            "surface": "G",
            "lighted": "0",
            "closed": "0",
            "le_ident": "15",
            "le_latitude_deg": "",
            "le_longitude_deg": "",
            "le_elevation_ft": "",
            "le_heading_degT": "",
            "le_displaced_threshold_ft": "",
            "he_ident": "33",
            "he_latitude_deg": "",
            "he_longitude_deg": "",
            "he_elevation_ft": "",
            "he_heading_degT": "",
            "he_displaced_threshold_ft": ""
        }
    ],
    "freqs": [
        {
            "id": "72164",
            "airport_ref": "27357",
            "airport_ident": "YBBA",
            "type": "CTAF",
            "description": "CTAF",
            "frequency_mhz": "127.1"
        },
        {
            "id": "72165",
            "airport_ref": "27357",
            "airport_ident": "YBBA",
            "type": "MISC",
            "description": "MISC",
            "frequency_mhz": "119.6"
        },
        {
            "id": "72166",
            "airport_ref": "27357",
            "airport_ident": "YBBA",
            "type": "MISC",
            "description": "MISC",
            "frequency_mhz": "122.1"
        }
    ],
    "country": {
        "id": "302764",
        "code": "AU",
        "name": "Australia",
        "continent": "OC",
        "wikipedia_link": "https://en.wikipedia.org/wiki/Australia",
        "keywords": ""
    },
    "region": {
        "id": "302969",
        "code": "AU-NSW",
        "local_code": "NSW",
        "name": "New South Wales",
        "continent": "OC",
        "iso_country": "AU",
        "wikipedia_link": "https://en.wikipedia.org/wiki/New_South_Wales",
        "keywords": ""
    }
}