{
    "id": "29801",
    "ident": "YCWA",
    "type": "small_airport",
    "name": "Coondewanna Airport",
    "latitude_deg": "-22.96669960022",
    "longitude_deg": "118.81300354004",
    "elevation_ft": "2300",
    "continent": "OC",
    "iso_country": "AU",
    "iso_region": "AU-WA",
    "municipality": "Coondewanna",
    "scheduled_service": "no",
    "gps_code": "YCWA",
    "iata_code": "CJF",
    "local_code": "",
    "home_link": "",
    "wikipedia_link": "https://en.wikipedia.org/wiki/Coondewanna_Airport",
    "keywords": "",
    "runways": [
        {
            "id": "327740",
            "airport_ref": "29801",
            "airport_ident": "YCWA",
            "length_ft": "6398",
            "width_ft": "",
            "surface": "CON",
            "lighted": "0",
            "closed": "0",
            "le_ident": "08",
            "le_latitude_deg": "",
            "le_longitude_deg": "",
            "le_elevation_ft": "",
            "le_heading_degT": "",
            "le_displaced_threshold_ft": "",
            "he_ident": "26",
            "he_latitude_deg": "",
            "he_longitude_deg": "",
            "he_elevation_ft": "",
            "he_heading_degT": "",
            "he_displaced_threshold_ft": ""
        }
    ],
    "country": {
        "id": "302764",
        "code": "AU",
        "name": "Australia",
        "continent": "OC",
        "wikipedia_link": "https://en.wikipedia.org/wiki/Australia",
        "keywords": ""
    },
    "region": {
        "id": "302976",
        "code": "AU-WA",
        "local_code": "WA",
        "name": "Western Australia",
        "continent": "OC",
        "iso_country": "AU",
        "wikipedia_link": "https://en.wikipedia.org/wiki/Western_Australia",
        "keywords": ""
    }
}