{
    "id": "41236",
    "ident": "ZA-0057",
    "type": "small_airport",
    "name": "Diamond Valley Airport",
    "latitude_deg": "-30.27199935913086",
    "longitude_deg": "29.39739990234375",
    "elevation_ft": "4900",
    "continent": "AF",
    "iso_country": "ZA",
    "iso_region": "ZA-NL",
    "municipality": "Swartberg",
    "scheduled_service": "no",
    "gps_code": "",
    "iata_code": "",
    "local_code": "",
    "home_link": "",
    "wikipedia_link": "",
    "keywords": "",
    "country": {
        "id": "302610",
        "code": "ZA",
        "name": "South Africa",
        "continent": "AF",
        "wikipedia_link": "https://en.wikipedia.org/wiki/South_Africa",
        "keywords": ""
    },
    "region": {
        "id": "306300",
        "code": "ZA-NL",
        "local_code": "NL",
        "name": "Kwazulu-Natal",
        "continent": "AF",
        "iso_country": "ZA",
        "wikipedia_link": "https://en.wikipedia.org/wiki/Kwazulu-Natal",
        "keywords": ""
    }
}